plover_unused_xtest_output/__init__.py
plover_unused_xtest_output-0.0.1.dist-info/LICENSE
plover_unused_xtest_output-0.0.1.dist-info/METADATA
plover_unused_xtest_output-0.0.1.dist-info/WHEEL
plover_unused_xtest_output-0.0.1.dist-info/entry_points.txt
plover_unused_xtest_output-0.0.1.dist-info/top_level.txt
plover_unused_xtest_output-0.0.1.dist-info/zip-safe
plover_unused_xtest_output-0.0.1.dist-info/RECORD
